[[{"location":"D:\\MyCode\\Hackathon\\Preperation_22012016\\GitPrepRepo\\MyHealthApp","type":"PROJECT","hints":{"PROJECT_NAME":"MyHealthApp"}},"MyHealthApp:MyHealthApp:0.0.1"],[{"location":"C:\\Users\\BharatRaju\\.m2\\repository\\joda-time\\joda-time\\2.7\\joda-time-2.7.jar","type":"JAR","hints":{}},"joda-time:joda-time:2.7.0"],[{"location":"D:\\MyCode\\Applications\\apache-tomcat-7.0.67\\lib\\servlet-api.jar","type":"JAR","hints":{}},"ABSENT"],[{"location":"D:\\MyCode\\Applications\\Java\\jdk1.7.0_79","type":"JRE","hints":{"EXECUTION_ENVIRONMENT":"JavaSE-1.7"}},"jre:jre:1.7.0"]]